shelly_restrict_login/secure.py
shelly_restrict-0.0.3.dist-info/LICENSE
shelly_restrict-0.0.3.dist-info/METADATA
shelly_restrict-0.0.3.dist-info/WHEEL
shelly_restrict-0.0.3.dist-info/entry_points.txt
shelly_restrict-0.0.3.dist-info/top_level.txt
shelly_restrict-0.0.3.dist-info/RECORD
