Metadata-Version: 2.1
Name: shelly-restrict
Version: 0.0.3
Summary: A Python package to restrict the login page of shelly-devices.
Home-page: https://github.com/Floplosion05/Shelly
Author: Florian Fuchs
Author-email: florfuchs2005@gmail.com
License: MIT
Keywords: shelly login shelly-login shelly-restrict-login http http-requests
Platform: UNKNOWN
Classifier: License :: OSI Approved :: MIT License
Classifier: Programming Language :: Python :: 3.7
Requires-Dist: requests (>=2.24.0)
Requires-Dist: passlib (>=1.7.4)
